ti_python_module/__init__.py
ti_python_module/err.py
ti_python_module/file_handler.py
ti_python_module/ti_draw.py
ti_python_module/ti_hub.py
ti_python_module/ti_plotlib.py
ti_python_module/ti_rover.py
ti_python_module/ti_system.py
ti_python_module-0.10.7.dist-info/LICENSE.md
ti_python_module-0.10.7.dist-info/METADATA
ti_python_module-0.10.7.dist-info/WHEEL
ti_python_module-0.10.7.dist-info/top_level.txt
ti_python_module-0.10.7.dist-info/RECORD
