Metadata-Version: 2.1
Name: ti-python-module
Version: 0.10.7
Summary: Texas Instruments Python Debugging and Programming Support
Home-page: UNKNOWN
Author: VampireTechnologyLord
Author-email: <elias.freund@ewe.net>
License: UNKNOWN
Keywords: python,ti,texas instruments
Platform: UNKNOWN
Classifier: Development Status :: 1 - Planning
Classifier: Intended Audience :: Developers
Classifier: Programming Language :: Python :: 3
Classifier: Operating System :: Unix
Classifier: Operating System :: MacOS
Classifier: Operating System :: Microsoft :: Windows
Classifier: Topic :: Utilities
License-File: LICENSE.md
